test_pypi_publish_workflow/__init__.py
test_pypi_publish_workflow/preprocessing.py
test_pypi_publish_workflow-1.1.0.dist-info/METADATA
test_pypi_publish_workflow-1.1.0.dist-info/WHEEL
test_pypi_publish_workflow-1.1.0.dist-info/RECORD
